LICENSE
investment_simulator/__init__.py
investment_simulator/allocations.py
investment_simulator/contributions.py
investment_simulator/portfolios.py
investment_simulator/tax.py
investment_simulator/utils.py
investment_simulator-0.2.1.2.dist-info/LICENSE
investment_simulator-0.2.1.2.dist-info/WHEEL
investment_simulator-0.2.1.2.dist-info/METADATA
investment_simulator-0.2.1.2.dist-info/RECORD
