Metadata-Version: 2.1
Name: investment-simulator
Version: 0.2.1.2
Summary: Library for simulating a persons investment portfolio over time based on risk and return
Home-page: https://github.com/jarden-sid/investment-simulator
License: MIT
Keywords: investments,portfolio
Author: Siddha Ishmael Ganesan
Author-email: siddha.ganesan@gmail.com
Requires-Python: >=3.8,<4.0
Classifier: License :: OSI Approved :: MIT License
Classifier: Programming Language :: Python :: 3
Classifier: Programming Language :: Python :: 3.8
Requires-Dist: numpy (>=1.20.rc1,<2.0)
Requires-Dist: pydantic (>=1.8.1,<2.0.0)
Requires-Dist: scipy (>=1.6.0,<2.0.0)
Project-URL: Repository, https://github.com/jarden-sid/investment-simulator
